logjson.py
logjson-2020.3.1.dist-info/LICENSE
logjson-2020.3.1.dist-info/WHEEL
logjson-2020.3.1.dist-info/METADATA
logjson-2020.3.1.dist-info/RECORD
